pyboxmaker/__init__.py
pyboxmaker/__main__.py
pyboxmaker/boxmaker.py
pyboxmaker/utils.py
pyboxmaker-1.0.dist-info/LICENSE
pyboxmaker-1.0.dist-info/METADATA
pyboxmaker-1.0.dist-info/WHEEL
pyboxmaker-1.0.dist-info/top_level.txt
pyboxmaker-1.0.dist-info/RECORD
